pythondata_cpu_lm32/__init__.py
pythondata_cpu_lm32/verilog/LICENSE.LATTICE
pythondata_cpu_lm32/verilog/README
pythondata_cpu_lm32/verilog/doc/Makefile
pythondata_cpu_lm32/verilog/doc/mmu.rst
pythondata_cpu_lm32/verilog/rtl/jtag_cores.v
pythondata_cpu_lm32/verilog/rtl/jtag_tap_spartan6.v
pythondata_cpu_lm32/verilog/rtl/lm32_adder.v
pythondata_cpu_lm32/verilog/rtl/lm32_addsub.v
pythondata_cpu_lm32/verilog/rtl/lm32_config.v.sample
pythondata_cpu_lm32/verilog/rtl/lm32_cpu.v
pythondata_cpu_lm32/verilog/rtl/lm32_dcache.v
pythondata_cpu_lm32/verilog/rtl/lm32_debug.v
pythondata_cpu_lm32/verilog/rtl/lm32_decoder.v
pythondata_cpu_lm32/verilog/rtl/lm32_dp_ram.v
pythondata_cpu_lm32/verilog/rtl/lm32_dtlb.v
pythondata_cpu_lm32/verilog/rtl/lm32_icache.v
pythondata_cpu_lm32/verilog/rtl/lm32_include.v
pythondata_cpu_lm32/verilog/rtl/lm32_instruction_unit.v
pythondata_cpu_lm32/verilog/rtl/lm32_interrupt.v
pythondata_cpu_lm32/verilog/rtl/lm32_itlb.v
pythondata_cpu_lm32/verilog/rtl/lm32_jtag.v
pythondata_cpu_lm32/verilog/rtl/lm32_load_store_unit.v
pythondata_cpu_lm32/verilog/rtl/lm32_logic_op.v
pythondata_cpu_lm32/verilog/rtl/lm32_mc_arithmetic.v
pythondata_cpu_lm32/verilog/rtl/lm32_multiplier.v
pythondata_cpu_lm32/verilog/rtl/lm32_ram.v
pythondata_cpu_lm32/verilog/rtl/lm32_shifter.v
pythondata_cpu_lm32/verilog/rtl/lm32_top.v
pythondata_cpu_lm32/verilog/test/.gitignore
pythondata_cpu_lm32/verilog/test/Makefile
pythondata_cpu_lm32/verilog/test/crt.S
pythondata_cpu_lm32/verilog/test/hello_world.c
pythondata_cpu_lm32/verilog/test/linker.ld
pythondata_cpu_lm32/verilog/test/lm32_config.v
pythondata_cpu_lm32/verilog/test/pipe1.S
pythondata_cpu_lm32/verilog/test/tb_lm32_system.v
pythondata_cpu_lm32/verilog/test/unittests/.gitignore
pythondata_cpu_lm32/verilog/test/unittests/Makefile
pythondata_cpu_lm32/verilog/test/unittests/crt.S
pythondata_cpu_lm32/verilog/test/unittests/linker.ld
pythondata_cpu_lm32/verilog/test/unittests/macros.inc
pythondata_cpu_lm32/verilog/test/unittests/test_add.S
pythondata_cpu_lm32-0.0.post199.dist-info/LICENSE
pythondata_cpu_lm32-0.0.post199.dist-info/METADATA
pythondata_cpu_lm32-0.0.post199.dist-info/WHEEL
pythondata_cpu_lm32-0.0.post199.dist-info/top_level.txt
pythondata_cpu_lm32-0.0.post199.dist-info/RECORD
