Metadata-Version: 2.1
Name: pythondata-cpu-lm32
Version: 0.0.post199
Summary: Python module containing verilog files for LatticeMico32 cpu.
Home-page: https://github.com/litex-hub/pythondata-cpu-lm32
Author: LiteX Authors
Author-email: litex@googlegroups.com
Project-URL: Bug Tracker, https://github.com/litex-hub/pythondata-cpu-lm32/issues
Project-URL: Source Code, https://github.com/litex-hub/pythondata-cpu-lm32
Classifier: Programming Language :: Python :: 3
Classifier: License :: OSI Approved :: Eclipse Public License 1.0 (EPL-1.0)
Classifier: Operating System :: OS Independent
Requires-Python: >=3.5
License-File: LICENSE
